src/__init__.py
src/py40kie.py
py40kie-0.2.2.dist-info/METADATA
py40kie-0.2.2.dist-info/WHEEL
py40kie-0.2.2.dist-info/entry_points.txt
py40kie-0.2.2.dist-info/licenses/LICENSE
py40kie-0.2.2.dist-info/RECORD
