Metadata-Version: 2.1
Name: py40kie
Version: 0.2.2
Summary: Command line Python program to extract army rules and unit cards from 10th edition Warhammer 40k indexes to create army list specific pdfs with reduced file size.
Project-URL: Homepage, https://github.com/Dragons-Ire/40k-index-pdf-extractor
Project-URL: Bug Tracker, https://github.com/Dragons-Ire/40k-index-pdf-extractor/issues
Author-email: Chris Austin <dragons.ire.oce@gmail.com>
License-File: LICENSE
Classifier: Environment :: Console
Classifier: Intended Audience :: End Users/Desktop
Classifier: License :: OSI Approved :: MIT License
Classifier: Operating System :: OS Independent
Classifier: Programming Language :: Python :: 3
Classifier: Programming Language :: Python :: 3.8
Classifier: Programming Language :: Python :: 3.9
Classifier: Programming Language :: Python :: 3.10
Classifier: Programming Language :: Python :: 3.11
Requires-Python: >=3.7
Requires-Dist: pypdf~=3.12.1
